jovian_data/__init__.py
jovian_data/_version.py
jovian_data/cli.py
jovian_data/utils/__init__.py
jovian_data/utils/constants.py
jovian_data/utils/datasets.py
jovian_data-0.1.2.dist-info/METADATA
jovian_data-0.1.2.dist-info/RECORD
jovian_data-0.1.2.dist-info/WHEEL
jovian_data-0.1.2.dist-info/entry_points.txt
jovian_data-0.1.2.dist-info/top_level.txt
