Metadata-Version: 2.1
Name: jovian-data
Version: 0.1.2
Summary: Jovian-data Python SDK
Home-page: https://jvn.io
Author: SwiftAce
Author-email: opensource@swiftace.ai
License: UNKNOWN
Platform: UNKNOWN
Classifier: Programming Language :: Python :: 3
Classifier: License :: OSI Approved :: MIT License
Classifier: Operating System :: OS Independent
